src/alu.v
// Computer Architecture CO2070 - Lab 02 (Part 1)
// Design: 8-bit ALU
// Team : 06
// Members : E/22/014 , E/22/035

// Operations:
// 000 - Forward DATA2
// 001 - Addition
// 010 - Bitwise AND
// 011 - Bitwise OR
//
// Unused SELECT values are handled safely
// by sending 0 to the output.


// Forward Unit
// RESULT = DATA2
// Delay = 1 time unit

module forward_unit(DATA2, RESULT);

    input  [7:0] DATA2;
    output reg [7:0] RESULT;

    always @(*)
    begin
        #1 RESULT = DATA2;
    end

endmodule


// Add Unit
// RESULT = DATA1 + DATA2
// Delay = 2 time units

module add_unit(DATA1, DATA2, RESULT);

    input  [7:0] DATA1, DATA2;
    output reg [7:0] RESULT;

    always @(*)
    begin
        #2 RESULT = DATA1 + DATA2;
    end

endmodule


// AND Unit
// RESULT = DATA1 & DATA2
// Delay = 1 time unit

module and_unit(DATA1, DATA2, RESULT);

    input  [7:0] DATA1, DATA2;
    output reg [7:0] RESULT;

    always @(*)
    begin
        #1 RESULT = DATA1 & DATA2;
    end

endmodule


// OR Unit
// RESULT = DATA1 | DATA2
// Delay = 1 time unit

module or_unit(DATA1, DATA2, RESULT);

    input  [7:0] DATA1, DATA2;
    output reg [7:0] RESULT;

    always @(*)
    begin
        #1 RESULT = DATA1 | DATA2;
    end

endmodule




// Main ALU Module

module alu(DATA1, DATA2, RESULT, SELECT);

    input  [7:0] DATA1, DATA2;
    input  [2:0] SELECT;

    output reg [7:0] RESULT;


    // wires to get outputs from each unit
    wire [7:0] forward_result;
    wire [7:0] add_result;
    wire [7:0] and_result;
    wire [7:0] or_result;


    
    // Unit Instantiations
    

    forward_unit f1(DATA2, forward_result);

    add_unit a1(DATA1, DATA2, add_result);

    and_unit and1(DATA1, DATA2, and_result);

    or_unit o1(DATA1, DATA2, or_result);


    
    // Select the required operation
    
    always @(*)
    begin

        case(SELECT)

            // Forward DATA2
            3'b000:
                RESULT = forward_result;

            // Addition
            3'b001:
                RESULT = add_result;

            // Bitwise AND
            3'b010:
                RESULT = and_result;

            // Bitwise OR
            3'b011:
                RESULT = or_result;

            // Unused SELECT values
            // Future operations can be added here
            default:
                RESULT = 8'b00000000;

        endcase

    end

endmodule

testbenches/alu_tb.v
// Computer Architecture CO2070 - Lab 02 (Part 1)
// Design: 8-bit ALU
// Team : 06
// Members : E/22/014 , E/22/035

`include "alu.v"

module alu_tb;

    // inputs to ALU
    reg [7:0] DATA1;
    reg [7:0] DATA2;
    reg [2:0] SELECT;

    // output from ALU
    wire [7:0] RESULT;


    // instantiate ALU module
    alu myalu(DATA1, DATA2, RESULT, SELECT);


    initial
    begin

        // generate waveform file for GTKWave
        $dumpfile("alu_wavedata.vcd");
        $dumpvars(0, alu_tb);


        //======================================================
        // Test 1 : Forward Operation
        // RESULT = DATA2
        //======================================================

        DATA1 = 8'd10;
        DATA2 = 8'd5;
        SELECT = 3'b000;

        #10;


        //======================================================
        // Test 2 : Addition
        // RESULT = DATA1 + DATA2
        //======================================================

        DATA1 = 8'd20;
        DATA2 = 8'd15;
        SELECT = 3'b001;

        #10;


        //======================================================
        // Test 3 : Bitwise AND
        //======================================================

        DATA1 = 8'b10101010;
        DATA2 = 8'b11001100;
        SELECT = 3'b010;

        #10;


        //======================================================
        // Test 4 : Bitwise OR
        //======================================================

        DATA1 = 8'b10101010;
        DATA2 = 8'b11001100;
        SELECT = 3'b011;

        #10;


        //======================================================
        // Test 5 : Unused SELECT value 100
        //======================================================

        DATA1 = 8'd50;
        DATA2 = 8'd25;
        SELECT = 3'b100;

        #10;


        //======================================================
        // Test 6 : Unused SELECT value 101
        //======================================================

        SELECT = 3'b101;

        #10;


        //======================================================
        // Test 7 : Unused SELECT value 110
        //======================================================

        SELECT = 3'b110;

        #10;


        //======================================================
        // Test 8 : Unused SELECT value 111
        //======================================================

        SELECT = 3'b111;

        #10;


        // finish simulation
        $finish;

    end


    // display values in terminal

    initial
    begin

        $monitor(
            "Time=%0d DATA1=%b DATA2=%b SELECT=%b RESULT=%b",
            $time,
            DATA1,
            DATA2,
            SELECT,
            RESULT
        );

    end

endmodule

testbenches/alu_wavedata.vcd
$date
	Sat Jun 06 22:06:37 2026
$end
$version
	Icarus Verilog
$end
$timescale
	1s
$end
$scope module alu_tb $end
$var wire 8 ! RESULT [7:0] $end
$var reg 8 " DATA1 [7:0] $end
$var reg 8 # DATA2 [7:0] $end
$var reg 3 $ SELECT [2:0] $end
$scope module myalu $end
$var wire 8 % DATA1 [7:0] $end
$var wire 8 & DATA2 [7:0] $end
$var wire 3 ' SELECT [2:0] $end
$var wire 8 ( or_result [7:0] $end
$var wire 8 ) forward_result [7:0] $end
$var wire 8 * and_result [7:0] $end
$var wire 8 + add_result [7:0] $end
$var reg 8 , RESULT [7:0] $end
$scope module a1 $end
$var wire 8 - DATA1 [7:0] $end
$var wire 8 . DATA2 [7:0] $end
$var reg 8 / RESULT [7:0] $end
$upscope $end
$scope module and1 $end
$var wire 8 0 DATA1 [7:0] $end
$var wire 8 1 DATA2 [7:0] $end
$var reg 8 2 RESULT [7:0] $end
$upscope $end
$scope module f1 $end
$var wire 8 3 DATA2 [7:0] $end
$var reg 8 4 RESULT [7:0] $end
$upscope $end
$scope module o1 $end
$var wire 8 5 DATA1 [7:0] $end
$var wire 8 6 DATA2 [7:0] $end
$var reg 8 7 RESULT [7:0] $end
$upscope $end
$upscope $end
$upscope $end
$enddefinitions $end
$comment Show the parameter values. $end
$dumpall
$end
#0
$dumpvars
bx 7
b101 6
b1010 5
bx 4
b101 3
bx 2
b101 1
b1010 0
bx /
b101 .
b1010 -
bx ,
bx +
bx *
bx )
bx (
b0 '
b101 &
b1010 %
b0 $
b101 #
b1010 "
bx !
$end
#1
b101 !
b101 ,
b101 )
b101 4
b1111 (
b1111 7
b0 *
b0 2
#2
b1111 +
b1111 /
#10
b1111 !
b1111 ,
b1 $
b1 '
b1111 #
b1111 &
b1111 .
b1111 1
b1111 3
b1111 6
b10100 "
b10100 %
b10100 -
b10100 0
b10100 5
#11
b1111 )
b1111 4
b100 *
b100 2
b11111 (
b11111 7
#12
b100011 !
b100011 ,
b100011 +
b100011 /
#20
b100 !
b100 ,
b10 $
b10 '
b11001100 #
b11001100 &
b11001100 .
b11001100 1
b11001100 3
b11001100 6
b10101010 "
b10101010 %
b10101010 -
b10101010 0
b10101010 5
#21
b10001000 !
b10001000 ,
b11001100 )
b11001100 4
b11101110 (
b11101110 7
b10001000 *
b10001000 2
#22
b1110110 +
b1110110 /
#30
b11101110 !
b11101110 ,
b11 $
b11 '
#40
b0 !
b0 ,
b100 $
b100 '
b11001 #
b11001 &
b11001 .
b11001 1
b11001 3
b11001 6
b110010 "
b110010 %
b110010 -
b110010 0
b110010 5
#41
b11001 )
b11001 4
b10000 *
b10000 2
b111011 (
b111011 7
#42
b1001011 +
b1001011 /
#50
b101 $
b101 '
#60
b110 $
b110 '
#70
b111 $
b111 '
