src/alu.v
// Computer Architecture CO2070 - Lab 04
// Design: 8-bit ALU with ZERO flag output for beq support
// Team  : 06
// Members : E/22/014, E/22/035

// Operations:
// 000 - Forward DATA2
// 001 - Addition
// 010 - Bitwise AND
// 011 - Bitwise OR
//
// Unused SELECT values are handled safely
// by sending 0 to the output.

// New output for Lab 4:
//   ZERO    is 1 when the subtraction result is all-zero,
//           used by the beq instruction to decide whether to branch.

`timescale 1ns/100ps


// Forward Unit
// RESULT = DATA2
// Delay = 1 time unit

module forward_unit(DATA2, RESULT);

    input  [7:0] DATA2;
    output reg [7:0] RESULT;

    always @(*)
    begin
        #1 RESULT = DATA2;
    end

endmodule


// Add Unit
// RESULT = DATA1 + DATA2
// Delay = 2 time units

module add_unit(DATA1, DATA2, RESULT);

    input  [7:0] DATA1, DATA2;
    output reg [7:0] RESULT;

    always @(*)
    begin
        #2 RESULT = DATA1 + DATA2;
    end

endmodule

// AND Unit
// RESULT = DATA1 & DATA2
// Delay = 1 time unit

module and_unit(DATA1, DATA2, RESULT);

    input  [7:0] DATA1, DATA2;
    output reg [7:0] RESULT;

    always @(*)
    begin
        #1 RESULT = DATA1 & DATA2;
    end

endmodule


// OR Unit
// RESULT = DATA1 | DATA2
// Delay = 1 time unit

module or_unit(DATA1, DATA2, RESULT);

    input  [7:0] DATA1, DATA2;
    output reg [7:0] RESULT;

    always @(*)
    begin
        #1 RESULT = DATA1 | DATA2;
    end

endmodule

// Main ALU Module
// New port: ZERO – HIGH (ZERO = 1) when the result of a subtract is 0.
// The ZERO flag is used by beq to decide whether to take the branch.

module alu(DATA1, DATA2, RESULT, SELECT, ZERO);

    input  [7:0] DATA1, DATA2;
    input  [2:0] SELECT;

    output reg [7:0] RESULT;

    // ZERO is 1 when RESULT == 0, used exclusively by beq.
    output ZERO;
    assign ZERO = (RESULT == 8'b00000000) ? 1'b1 : 1'b0;

    // wires to get outputs from each unit
    wire [7:0] forward_result;
    wire [7:0] add_result;
    wire [7:0] and_result;
    wire [7:0] or_result;


    // Unit Instantiations
    forward_unit f1(DATA2, forward_result);
    add_unit a1(DATA1, DATA2, add_result);
    and_unit and1(DATA1, DATA2, and_result);
    or_unit o1(DATA1, DATA2, or_result);


    // Select the required operation

    always @(*)
    begin

        case(SELECT)

            // Forward DATA2
            3'b000:
                RESULT = forward_result;

            // Addition
            3'b001:
                RESULT = add_result;

            // Bitwise AND
            3'b010:
                RESULT = and_result;

            // Bitwise OR
            3'b011:
                RESULT = or_result;

            // Unused SELECT values
            // Future operations can be added here
            default:
                RESULT = 8'b00000000;

        endcase

    end

endmodule

src/reg_file.v
// Computer Architecture CO2070 - Lab 02
// Design: Register File of Simple Processor
// Author: Kisaru Liyanage
// Team : 06
// Members : E/22/014 , E/22/035

// Register File Module

`timescale 1ns/100ps

module reg_file(
    IN,
    OUT1,
    OUT2,
    INADDRESS,
    OUT1ADDRESS,
    OUT2ADDRESS,
    WRITE,
    CLK,
    RESET
);


// Input Ports

// data input
input [7:0] IN;

// register addresses
input [2:0] INADDRESS;
input [2:0] OUT1ADDRESS;
input [2:0] OUT2ADDRESS;

// control signals
input WRITE;
input CLK;
input RESET;


// Output Ports

// output values from registers
output reg [7:0] OUT1;
output reg [7:0] OUT2;


// Register Array
// 8 registers
// each register contains 8 bits

reg [7:0] registers [7:0];


// Asynchronous Read
// outputs change immediately when:
// - read address changes
// - register values change

always @(
    OUT1ADDRESS or
    OUT2ADDRESS or
    registers[0] or
    registers[1] or
    registers[2] or
    registers[3] or
    registers[4] or
    registers[5] or
    registers[6] or
    registers[7]
)

begin

    // read delay
    #2;

    // read data from selected registers
    OUT1 = registers[OUT1ADDRESS];
    OUT2 = registers[OUT2ADDRESS];

end


// Synchronous Write and Reset
// operations happen only at positive clock edge

always @(posedge CLK)

begin

    // Reset all registers

    if(RESET)

    begin

        // reset delay
        #1;

        registers[0] = 8'b00000000;
        registers[1] = 8'b00000000;
        registers[2] = 8'b00000000;
        registers[3] = 8'b00000000;
        registers[4] = 8'b00000000;
        registers[5] = 8'b00000000;
        registers[6] = 8'b00000000;
        registers[7] = 8'b00000000;

    end


    // Write operation

    else if(WRITE)

    begin

        // write delay
        #1;

        // write input data into selected register
        registers[INADDRESS] = IN;

    end

end

endmodule

src/pc.v
// Computer Architecture CO2070 - Lab 04
// Design: Program Counter (PC) Module with Branch/Jump Support
// Team  : 06
// Members : E/22/014, E/22/035

// PC now accepts an external PC_IN so the cpu can mux between
// PC+4 (sequential) and the branch/jump target.
// PC_SEL = 0  :  PC_IN = PC + 4   (normal sequential execution)
// PC_SEL = 1  :  PC_IN = branch/jump target from the branch adder

`timescale 1ns/100ps

module pc(PC, PC_IN, CLK, RESET);

    // Current PC value visible to instruction memory and cpu
    output reg [31:0] PC;

    // Next PC already selected by the cpu-level mux (PC+4 or branch target)
    input  [31:0] PC_IN;

    input         CLK;
    input         RESET;


    // PC + 4 adder
    // Runs in parallel with instruction memory read (#1 latency per timing diagram)

    wire [31:0] PC_PLUS4;
    assign #1 PC_PLUS4 = PC + 32'd4;


    // PC register: synchronous update on rising clock edge

    always @(posedge CLK)
    begin

        if (RESET)
        begin
            // Restart execution from address 0
            #1 PC = 32'b0;
        end
        else
        begin
            // Load whichever PC source the cpu selected
            #1 PC = PC_IN;
        end

    end

endmodule

src/cpu.v
// Computer Architecture CO2070 - Lab 04
// Design: Top-Level CPU Module with Flow Control (j and beq)
// Team  : 06
// Members : E/22/014, E/22/035

// OPCODE table (from CO2070Assembler.c):
//   8'b00000000  loadi
//   8'b00000001  mov
//   8'b00000010  add
//   8'b00000011  sub
//   8'b00000100  and
//   8'b00000101  or

// ALU SELECT encoding:
//   3'b000  forward DATA2   (mov, loadi)
//   3'b001  add             (add, sub)
//   3'b010  and             (and)
//   3'b011  or              (or)

// Timing per the lab diagram (single-cycle, 8 time-unit clock period):
//   PC Update            #1
//   Instruction Mem Read #2  (in testbench)
//   PC+4 Adder             #1   (runs in parallel with mem read, inside pc.v)
//   Decode               #1
//   2's Complement       #1  (sub only, in parallel with register read)
//   Register Read        #2  (in reg_file)
//   ALU                  #2  (add/sub) or #1 (and/or/mov/loadi)
//   Register Write       #1  (in reg_file)
//   PC+4 Adder           #1  (runs in parallel with mem read)

`include "alu.v"
`include "reg_file.v"
`include "pc.v"

`timescale 1ns/100ps

module cpu(PC, INSTRUCTION, CLK, RESET);

    // Outputs
    output [31:0] PC;

    // Inputs
    input  [31:0] INSTRUCTION;
    input         CLK;
    input         RESET;


    // Wires coming out of the instruction decode stage

    wire [7:0]  OPCODE;           // bits [31:24]
    wire [7:0]  RD_ADDR;          // bits [23:16]
    wire [7:0]  RT_ADDR;          // bits [15:8]
    wire [7:0]  RS_ADDR;          // bits [7:0]
    wire [7:0]  IMMEDIATE;        // bits [7:0]   -- same field as RS_ADDR, used by loadi

    // Decode
    assign OPCODE    = INSTRUCTION[31:24];
    assign RD_ADDR   = INSTRUCTION[23:16];   // full 8-bit field; register address uses [2:0]
    assign RT_ADDR   = INSTRUCTION[15:8];
    assign RS_ADDR   = INSTRUCTION[7:0];
    assign IMMEDIATE = INSTRUCTION[7:0];     // same bits -- used by loadi

    // Control signals (all generated combinationally after decode)
    reg [2:0] ALUOP;         // selects ALU operation
    reg       WRITEENABLE;   // enables register-file write
    reg       MUX_IMM_SEL;   // 1 = feed IMMEDIATE into ALU DATA2  (loadi)
    reg       MUX_NEG_SEL;   // 1 = negate REGOUT2 before ALU      (sub, beq)
    reg       JUMP;          // 1 = unconditional jump (j)
    reg       BRANCH;        // 1 = conditional branch  (beq)


    // PC Next-value Logic 

    // PC+4 is computed inside pc.v with #1 delay.
    // The branch/jump target adder below runs in parallel with the ALU (#2 delay).

    //   Branch/jump target:
    //   target = (PC + 4) + sign_extended(OFFSET) * 4
    //   The offset is stored in RD_ADDR (bits[23:16]) for j.
    //   For beq, it is also stored in RD_ADDR.
    //   The assembler stores the raw offset value; multiplying by 4 aligns
    //   the byte address because each instruction is 4 bytes wide.

    // PC+4 wire – computed by the pc module with #1 delay
    wire [31:0] PC_PLUS4;
    assign #1 PC_PLUS4 = PC + 32'd4;

    // Sign-extend the 8-bit offset field (RD_ADDR) to 32 bits, then multiply by 4
    wire [31:0] OFFSET_EXTENDED;
    assign OFFSET_EXTENDED = {{22{RD_ADDR[7]}}, RD_ADDR, 2'b00};

    // Branch/jump target adder – latency #2 (runs in parallel with ALU)
    wire [31:0] BRANCH_TARGET;
    assign #2 BRANCH_TARGET = PC_PLUS4 + OFFSET_EXTENDED;

    // ZERO flag from ALU – used by beq to detect RT == RS
    wire ZERO;

    // PC_SEL decides what goes into the PC register next cycle:
    //   j          -> always take the jump target
    //   beq + ZERO -> take the branch target only when registers are equal
    //   otherwise  -> take PC + 4 (sequential)
    wire PC_SEL;
    assign PC_SEL = JUMP | (BRANCH & ZERO);

    // Next PC mux: feeds the PC module
    wire [31:0] PC_NEXT;
    assign PC_NEXT = (PC_SEL) ? BRANCH_TARGET : PC_PLUS4;

    // PC module instantiation
    pc mypc(
        .PC    (PC),
        .PC_IN (PC_NEXT),
        .CLK   (CLK),
        .RESET (RESET)
    );


    // ── Register File Connections ────────────────────────────────────────────

    wire [7:0] REGOUT1;    // read data from RT (source 1)
    wire [7:0] REGOUT2;    // read data from RS (source 2)
    wire [7:0] ALURESULT;  // ALU output, written back to RD

    reg_file rf(
        .IN          (ALURESULT),
        .OUT1        (REGOUT1),
        .OUT2        (REGOUT2),
        .INADDRESS   (RD_ADDR[2:0]),
        .OUT1ADDRESS (RT_ADDR[2:0]),
        .OUT2ADDRESS (RS_ADDR[2:0]),
        .WRITE       (WRITEENABLE),
        .CLK         (CLK),
        .RESET       (RESET)
    );


    // Two's complement unit
    // Negates REGOUT2 for the sub instruction. Delay = #1.
    wire [7:0] NEGATED_REGOUT2;
    assign #1 NEGATED_REGOUT2 = ~REGOUT2 + 8'b00000001;


    //   MUX 1: select between REGOUT2 and its two's complement
    //   MUX_NEG_SEL = 0  ->  REGOUT2          (add, and, or, mov)
    //   MUX_NEG_SEL = 1  ->  NEGATED_REGOUT2  (sub)
    wire [7:0] MUX1_OUT;
    assign MUX1_OUT = (MUX_NEG_SEL) ? NEGATED_REGOUT2 : REGOUT2;


    // MUX 2: select between MUX1_OUT and IMMEDIATE
    //   MUX_IMM_SEL = 0  ->  MUX1_OUT   (register instructions)
    //   MUX_IMM_SEL = 1  ->  IMMEDIATE  (loadi)
    wire [7:0] ALU_DATA2;
    assign ALU_DATA2 = (MUX_IMM_SEL) ? IMMEDIATE : MUX1_OUT;


    // ALU instantiation
    alu myalu(
        .DATA1  (REGOUT1),
        .DATA2  (ALU_DATA2),
        .RESULT (ALURESULT),
        .SELECT (ALUOP),
        .ZERO   (ZERO)
    );


    // Control Unit (combinational)
    // Decodes OPCODE and sets all control signals + #1 decode delay
    
    always @(OPCODE)
    begin

        // Default: safe values that cause no side effects
        WRITEENABLE = 1'b0;
        MUX_IMM_SEL = 1'b0;
        MUX_NEG_SEL = 1'b0;
        ALUOP       = 3'b000;
        JUMP        = 1'b0;
        BRANCH      = 1'b0;

        // Apply decode latency of 1 time unit
        #1;

        case (OPCODE)

            // loadi  RD, IMM
            // Load the 8-bit immediate (bits [7:0]) into register RD.
            // ALU forwards IMMEDIATE directly (MUX_IMM_SEL=1, ALUOP=000).
            
            8'b00000000:
            begin
                WRITEENABLE = 1'b1;
                MUX_IMM_SEL = 1'b1;   // route immediate into ALU DATA2
                MUX_NEG_SEL = 1'b0;
                ALUOP       = 3'b000;  // forward DATA2
            end

            // mov  RD, RT
            // Copy the value in register RT to register RD.
            // RS bits are ignored. ALU forwards REGOUT1 through forward unit.
            
            8'b00000001:
            begin
                WRITEENABLE = 1'b1;
                MUX_IMM_SEL = 1'b0;
                MUX_NEG_SEL = 1'b0;
                ALUOP       = 3'b000;  // forward DATA2 (REGOUT2 holds RT)
            end

            // add  RD, RT, RS
            // ALURESULT = REGOUT1 + REGOUT2
            8'b00000010:
            begin
                WRITEENABLE = 1'b1;
                MUX_IMM_SEL = 1'b0;
                MUX_NEG_SEL = 1'b0;
                ALUOP       = 3'b001;  // add
            end

            // sub  RD, RT, RS
            // ALURESULT = REGOUT1 - REGOUT2 = REGOUT1 + (~REGOUT2 + 1)
            // We negate REGOUT2 using the two's complement unit,
            // then feed the result to the adder.
            
            8'b00000011:
            begin
                WRITEENABLE = 1'b1;
                MUX_IMM_SEL = 1'b0;
                MUX_NEG_SEL = 1'b1;   // negate REGOUT2
                ALUOP       = 3'b001;  // add (of negated operand)
            end

            // and  RD, RT, RS
            // ALURESULT = REGOUT1 & REGOUT2
            
            8'b00000100:
            begin
                WRITEENABLE = 1'b1;
                MUX_IMM_SEL = 1'b0;
                MUX_NEG_SEL = 1'b0;
                ALUOP       = 3'b010;  // bitwise AND
            end

            // or  RD, RT, RS
            // ALURESULT = REGOUT1 | REGOUT2
            
            8'b00000101:
            begin
                WRITEENABLE = 1'b1;
                MUX_IMM_SEL = 1'b0;
                MUX_NEG_SEL = 1'b0;
                ALUOP       = 3'b011;  // bitwise OR
            end

            // j  OFFSET
            // Unconditional jump: PC = (PC+4) + sign_ext(OFFSET) * 4
            // Bits [15:0] are ignored.  OFFSET is in RD_ADDR (bits [23:16]).
            // WRITEENABLE stays 0 – no register is modified.
            // JUMP = 1 forces PC_SEL high, overriding the sequential path.

            8'b00000110:
            begin
                WRITEENABLE = 1'b0;
                MUX_IMM_SEL = 1'b0;
                MUX_NEG_SEL = 1'b0;
                ALUOP       = 3'b000;  // ALU not used – forward is harmless
                JUMP        = 1'b1;    // take the branch/jump target unconditionally
                BRANCH      = 1'b0;
            end

            // beq  OFFSET, RT, RS
            // Branch if RT == RS: PC = (PC+4) + sign_ext(OFFSET) * 4
            // RT == RS is detected by subtracting RS from RT and checking ZERO.
            // OFFSET is in RD_ADDR (bits [23:16]).
            // WRITEENABLE stays 0 – registers are compared, not written.
            // BRANCH = 1 enables the ZERO check in the PC mux.

            8'b00000111:
            begin
                WRITEENABLE = 1'b0;
                MUX_IMM_SEL = 1'b0;
                MUX_NEG_SEL = 1'b1;   // negate RS so ALU computes RT - RS
                ALUOP       = 3'b001;  // subtract to produce ZERO flag
                JUMP        = 1'b0;
                BRANCH      = 1'b1;   // branch if ALU result is zero
            end

            // Default: unrecognised opcode -- do nothing, don't write
            
            default:
            begin
                WRITEENABLE = 1'b0;
                MUX_IMM_SEL = 1'b0;
                MUX_NEG_SEL = 1'b0;
                ALUOP       = 3'b000;
                JUMP        = 1'b0;
                BRANCH      = 1'b0;
            end

        endcase

    end

endmodule

testbenches/cpu_tb(L4).v
// Computer Architecture CO2070 - Lab 04
// Design: Testbench for Lab 4 CPU (j and beq instructions)
// Team  : 06
// Members : E/22/014, E/22/035

// Test program overview:
//   loadi r1, 10          // r1 = 10
//   loadi r2, 10          // r2 = 10
//   loadi r3, 5           // r3 = 5
//   beq   +1, r1, r2      // r1 == r2, so skip next instruction (branch taken)
//   loadi r4, 0xFF        // ** skipped **
//   loadi r4, 0xBB        // r4 = 0xBB  (first instruction after branch)
//   beq   +1, r1, r3      // r1 != r3, so NOT taken (branch not taken)
//   loadi r5, 0xAA        // r5 = 0xAA  (executed because branch not taken)
//   j     +1              // jump forward 1 instruction (skip next)
//   loadi r6, 0xDE        // ** skipped by j **
//   loadi r6, 0xFF        // r6 = 0xFF  (first instruction after jump target)
//   loadi r7, 0x77        // r7 = 0x77  (normal sequential)

`include "cpu.v"

`timescale 1ns/100ps

module cpu_tb;

    reg  CLK, RESET;
    wire [31:0] PC;
    wire [31:0] INSTRUCTION;

    // Instruction memory – 1 KB byte array
    reg [7:0] instr_mem [0:1023];

    // Instruction fetch with memory access delay (#2 per timing diagram)
    assign #2 INSTRUCTION = {
        instr_mem[PC],
        instr_mem[PC + 1],
        instr_mem[PC + 2],
        instr_mem[PC + 3]
    };

    // ── Instruction Memory Initialisation ────────────────────────────────────
    // Each instruction occupies 4 bytes (big-endian):
    //   [0] = OPCODE, [1] = RD/OFFSET, [2] = RT, [3] = RS/IMM

    initial
    begin

        // ── Instruction 0 (address 0x00): loadi r1, 10 ──────────────────────
        instr_mem[0]  = 8'h00;   // OPCODE loadi
        instr_mem[1]  = 8'h01;   // RD = r1
        instr_mem[2]  = 8'h00;   // RT ignored
        instr_mem[3]  = 8'h0A;   // IMM = 10

        // ── Instruction 1 (address 0x04): loadi r2, 10 ──────────────────────
        instr_mem[4]  = 8'h00;
        instr_mem[5]  = 8'h02;   // RD = r2
        instr_mem[6]  = 8'h00;
        instr_mem[7]  = 8'h0A;   // IMM = 10

        // ── Instruction 2 (address 0x08): loadi r3, 5 ───────────────────────
        instr_mem[8]  = 8'h00;
        instr_mem[9]  = 8'h03;   // RD = r3
        instr_mem[10] = 8'h00;
        instr_mem[11] = 8'h05;   // IMM = 5

        // ── Instruction 3 (address 0x0C): beq +1, r1, r2 ────────────────────
        // r1 == r2 (both 10), so branch is TAKEN.
        // OFFSET = 0x01 means skip 1 instruction forward from PC+4
        // Target = (0x0C + 4) + (1 * 4) = 0x14
        instr_mem[12] = 8'h07;   // OPCODE beq
        instr_mem[13] = 8'h01;   // OFFSET = +1
        instr_mem[14] = 8'h01;   // RT = r1
        instr_mem[15] = 8'h02;   // RS = r2

        // ── Instruction 4 (address 0x10): loadi r4, 0xFF  (SHOULD BE SKIPPED) ─
        instr_mem[16] = 8'h00;
        instr_mem[17] = 8'h04;   // RD = r4
        instr_mem[18] = 8'h00;
        instr_mem[19] = 8'hFF;   // IMM = 0xFF (must NOT appear in r4)

        // ── Instruction 5 (address 0x14): loadi r4, 0xBB ────────────────────
        // Execution resumes here after the taken beq above
        instr_mem[20] = 8'h00;
        instr_mem[21] = 8'h04;   // RD = r4
        instr_mem[22] = 8'h00;
        instr_mem[23] = 8'hBB;   // IMM = 0xBB (r4 should become 0xBB)

        // ── Instruction 6 (address 0x18): beq +1, r1, r3 ────────────────────
        // r1 = 10, r3 = 5, they are NOT equal, branch NOT taken.
        // Execution continues sequentially to 0x1C.
        instr_mem[24] = 8'h07;   // OPCODE beq
        instr_mem[25] = 8'h01;   // OFFSET = +1
        instr_mem[26] = 8'h01;   // RT = r1
        instr_mem[27] = 8'h03;   // RS = r3

        // ── Instruction 7 (address 0x1C): loadi r5, 0xAA ────────────────────
        // Runs because the preceding beq was NOT taken
        instr_mem[28] = 8'h00;
        instr_mem[29] = 8'h05;   // RD = r5
        instr_mem[30] = 8'h00;
        instr_mem[31] = 8'hAA;   // IMM = 0xAA (r5 should become 0xAA)

        // ── Instruction 8 (address 0x20): j +1 ──────────────────────────────
        // Unconditional jump forward 1 instruction.
        // OFFSET = 0x01. Bits[15:0] are ignored.
        // Target = (0x20 + 4) + (1 * 4) = 0x28
        instr_mem[32] = 8'h06;   // OPCODE j
        instr_mem[33] = 8'h01;   // OFFSET = +1
        instr_mem[34] = 8'h00;   // ignored
        instr_mem[35] = 8'h00;   // ignored

        // ── Instruction 9 (address 0x24): loadi r6, 0xDE  (SHOULD BE SKIPPED) ─
        instr_mem[36] = 8'h00;
        instr_mem[37] = 8'h06;   // RD = r6
        instr_mem[38] = 8'h00;
        instr_mem[39] = 8'hDE;   // IMM = 0xDE (must NOT appear in r6)

        // ── Instruction 10 (address 0x28): loadi r6, 0xFF ───────────────────
        // Execution resumes here after the j above
        instr_mem[40] = 8'h00;
        instr_mem[41] = 8'h06;   // RD = r6
        instr_mem[42] = 8'h00;
        instr_mem[43] = 8'hFF;   // IMM = 0xFF (r6 should become 0xFF)

        // ── Instruction 11 (address 0x2C): loadi r7, 0x77 ───────────────────
        instr_mem[44] = 8'h00;
        instr_mem[45] = 8'h07;   // RD = r7
        instr_mem[46] = 8'h00;
        instr_mem[47] = 8'h77;   // IMM = 0x77 (r7 should become 0x77)

    end

    // ── DUT Instantiation ────────────────────────────────────────────────────

    cpu mycpu(PC, INSTRUCTION, CLK, RESET);

    // ── Simulation Control ───────────────────────────────────────────────────

    initial
    begin

        // Waveform dump for GTKWave
        $dumpfile("cpu_wavedata.vcd");
        $dumpvars(0, cpu_tb);

        CLK   = 1'b0;
        RESET = 1'b0;

        // Assert RESET for one full clock period to initialise the PC and registers
        #2  RESET = 1'b1;
        #10 RESET = 1'b0;

        // Run long enough to execute all 12 instructions
        // 12 instructions x 8 ns/cycle + reset overhead = well under 200 ns
        #200
        $finish;

    end

    // Clock: period = 8 ns  (toggle every 4 ns)
    always
        #4 CLK = ~CLK;

endmodule

testbenches/cpu_wavedata(L4).vcd
$date
	Tue Jun 16 08:41:19 2026
$end
$version
	Icarus Verilog
$end
$timescale
	100ps
$end
$scope module cpu_tb $end
$var wire 32 ! PC [31:0] $end
$var wire 32 " INSTRUCTION [31:0] $end
$var reg 1 # CLK $end
$var reg 1 $ RESET $end
$scope module mycpu $end
$var wire 1 # CLK $end
$var wire 32 % INSTRUCTION [31:0] $end
$var wire 1 & PC_SEL $end
$var wire 1 $ RESET $end
$var wire 1 ' ZERO $end
$var wire 8 ( RT_ADDR [7:0] $end
$var wire 8 ) RS_ADDR [7:0] $end
$var wire 8 * REGOUT2 [7:0] $end
$var wire 8 + REGOUT1 [7:0] $end
$var wire 8 , RD_ADDR [7:0] $end
$var wire 32 - PC_PLUS4 [31:0] $end
$var wire 32 . PC_NEXT [31:0] $end
$var wire 32 / PC [31:0] $end
$var wire 8 0 OPCODE [7:0] $end
$var wire 32 1 OFFSET_EXTENDED [31:0] $end
$var wire 8 2 NEGATED_REGOUT2 [7:0] $end
$var wire 8 3 MUX1_OUT [7:0] $end
$var wire 8 4 IMMEDIATE [7:0] $end
$var wire 32 5 BRANCH_TARGET [31:0] $end
$var wire 8 6 ALU_DATA2 [7:0] $end
$var wire 8 7 ALURESULT [7:0] $end
$var reg 3 8 ALUOP [2:0] $end
$var reg 1 9 BRANCH $end
$var reg 1 : JUMP $end
$var reg 1 ; MUX_IMM_SEL $end
$var reg 1 < MUX_NEG_SEL $end
$var reg 1 = WRITEENABLE $end
$scope module myalu $end
$var wire 8 > DATA2 [7:0] $end
$var wire 3 ? SELECT [2:0] $end
$var wire 8 @ or_result [7:0] $end
$var wire 8 A forward_result [7:0] $end
$var wire 8 B and_result [7:0] $end
$var wire 8 C add_result [7:0] $end
$var wire 1 ' ZERO $end
$var wire 8 D DATA1 [7:0] $end
$var reg 8 E RESULT [7:0] $end
$scope module a1 $end
$var wire 8 F DATA2 [7:0] $end
$var wire 8 G DATA1 [7:0] $end
$var reg 8 H RESULT [7:0] $end
$upscope $end
$scope module and1 $end
$var wire 8 I DATA2 [7:0] $end
$var wire 8 J DATA1 [7:0] $end
$var reg 8 K RESULT [7:0] $end
$upscope $end
$scope module f1 $end
$var wire 8 L DATA2 [7:0] $end
$var reg 8 M RESULT [7:0] $end
$upscope $end
$scope module o1 $end
$var wire 8 N DATA2 [7:0] $end
$var wire 8 O DATA1 [7:0] $end
$var reg 8 P RESULT [7:0] $end
$upscope $end
$upscope $end
$scope module mypc $end
$var wire 1 # CLK $end
$var wire 32 Q PC_IN [31:0] $end
$var wire 1 $ RESET $end
$var wire 32 R PC_PLUS4 [31:0] $end
$var reg 32 S PC [31:0] $end
$upscope $end
$scope module rf $end
$var wire 1 # CLK $end
$var wire 8 T IN [7:0] $end
$var wire 3 U INADDRESS [2:0] $end
$var wire 3 V OUT1ADDRESS [2:0] $end
$var wire 3 W OUT2ADDRESS [2:0] $end
$var wire 1 $ RESET $end
$var wire 1 = WRITE $end
$var reg 8 X OUT1 [7:0] $end
$var reg 8 Y OUT2 [7:0] $end
$upscope $end
$upscope $end
$upscope $end
$enddefinitions $end
$comment Show the parameter values. $end
$dumpall
$end
#0
$dumpvars
bx Y
bx X
bx W
bx V
bx U
bx T
bx S
bx R
bx Q
bx P
bx O
bx N
bx M
bx L
bx K
bx J
bx I
bx H
bx G
bx F
bx E
bx D
bx C
bx B
bx A
bx @
bx ?
bx >
x=
x<
x;
x:
x9
bx 8
bx 7
bx 6
bx 5
bx 4
bx 3
bx 2
bx00 1
bx 0
bx /
bx .
bx -
bx ,
bx +
bx *
bx )
bx (
x'
x&
bx %
0$
0#
bx "
bx !
$end
#20
1$
#40
1#
#50
b0 !
b0 /
b0 S
#60
b100 R
b100 -
#70
b100 .
b100 Q
0&
09
0:
b0 8
b0 ?
0<
0;
0=
b1 U
b0 V
b10 W
b0 0
b100 1
b1 ,
b0 (
b1010 )
b1010 4
b10000000000001010 "
b10000000000001010 %
#80
b1010 6
b1010 >
b1010 F
b1010 I
b1010 L
b1010 N
1;
1=
0#
#90
0'
b1010 7
b1010 E
b1010 T
b0 3
b1010 @
b1010 P
b0 B
b0 K
b1010 A
b1010 M
b0 *
b0 Y
b0 +
b0 D
b0 G
b0 J
b0 O
b0 X
b1000 5
#100
b0 2
b1010 C
b1010 H
#120
1#
0$
#130
b100 !
b100 /
b100 S
#140
b1000 .
b1000 Q
b1000 R
b1000 -
#150
b10 U
b1000 1
b10 ,
b100000000000001010 "
b100000000000001010 %
#160
0#
#170
b10000 5
#200
1#
#210
b1000 !
b1000 /
b1000 S
#220
b1100 .
b1100 Q
b1100 R
b1100 -
#230
b11 U
b101 W
b101 6
b101 >
b101 F
b101 I
b101 L
b101 N
b1010 3
b1100 1
b11 ,
b101 )
b101 4
b1010 *
b1010 Y
b110000000000000101 "
b110000000000000101 %
#240
b101 7
b101 E
b101 T
b101 @
b101 P
b101 A
b101 M
b11110110 2
0#
#250
b0 3
b0 *
b0 Y
b101 C
b101 H
b11000 5
#260
b0 2
#280
1#
#290
b1100 !
b1100 /
b1100 S
#300
b10000 .
b10000 Q
b10000 R
b10000 -
#310
0;
0=
b1 U
b1 V
b10 W
b0 6
b0 >
b0 F
b0 I
b0 L
b0 N
b111 0
b100 1
b1 ,
b1 (
b10 )
b10 4
b111000000010000000100000010 "
b111000000010000000100000010 %
#320
b0 @
b0 P
b0 A
b0 M
19
b1 8
b1 ?
1<
0#
#330
b10100 .
b10100 Q
1&
1'
b0 7
b0 E
b0 T
b1010 *
b1010 Y
b1010 +
b1010 D
b1010 G
b1010 J
b1010 O
b1010 X
b0 C
b0 H
b10100 5
#340
b11110110 6
b11110110 >
b11110110 F
b11110110 I
b11110110 L
b11110110 N
b11110110 3
b11110110 2
b1010 @
b1010 P
#350
b11111110 @
b11111110 P
b10 B
b10 K
b11110110 A
b11110110 M
#360
1#
#370
b10100 !
b10100 /
b10100 S
#380
b11000 R
b11000 -
#390
b11000 .
b11000 Q
0&
0'
b1010 6
b1010 >
b1010 F
b1010 I
b1010 L
b1010 N
b11110110 7
b11110110 E
b11110110 T
b1010 3
09
b0 8
b0 ?
0<
b100 U
b0 V
b11 W
b0 0
b10000 1
b100 ,
b0 (
b10111011 )
b10111011 4
b1000000000010111011 "
b1000000000010111011 %
#400
b1010 7
b1010 E
b1010 T
b10111011 6
b10111011 >
b10111011 F
b10111011 I
b10111011 L
b10111011 N
b1010 B
b1010 K
b1010 @
b1010 P
b1010 A
b1010 M
1;
1=
0#
#410
b10111011 7
b10111011 E
b10111011 T
b101 3
b10111011 @
b10111011 P
b0 B
b0 K
b10111011 A
b10111011 M
b10111011 C
b10111011 H
b101 *
b101 Y
b0 +
b0 D
b0 G
b0 J
b0 O
b0 X
b101000 5
#420
b11111011 2
#440
1#
#450
b11000 !
b11000 /
b11000 S
#460
b11100 .
b11100 Q
b11100 R
b11100 -
#470
0;
0=
b1 U
b1 V
b101 6
b101 >
b101 F
b101 I
b101 L
b101 N
b111 0
b100 1
b1 ,
b1 (
b11 )
b11 4
b111000000010000000100000011 "
b111000000010000000100000011 %
#480
b11111011 6
b11111011 >
b11111011 F
b11111011 I
b11111011 L
b11111011 N
b11111011 3
b101 @
b101 P
b101 A
b101 M
19
b1 8
b1 ?
1<
0#
#490
b11111011 7
b11111011 E
b11111011 T
b11111011 @
b11111011 P
b1010 B
b1010 K
b11111011 A
b11111011 M
b1010 +
b1010 D
b1010 G
b1010 J
b1010 O
b1010 X
b11111011 C
b11111011 H
b100000 5
#510
b101 7
b101 E
b101 T
b101 C
b101 H
#520
1#
#530
b11100 !
b11100 /
b11100 S
#540
b100000 .
b100000 Q
b100000 R
b100000 -
#550
b101 6
b101 >
b101 F
b101 I
b101 L
b101 N
b11111011 7
b11111011 E
b11111011 T
b101 3
09
b0 8
b0 ?
0<
b101 U
b0 V
b10 W
b0 0
b10100 1
b101 ,
b0 (
b10101010 )
b10101010 4
b1010000000010101010 "
b1010000000010101010 %
#560
b101 7
b101 E
b101 T
b10101010 6
b10101010 >
b10101010 F
b10101010 I
b10101010 L
b10101010 N
b0 B
b0 K
b1111 @
b1111 P
b101 A
b101 M
1;
1=
0#
#570
b10101010 7
b10101010 E
b10101010 T
b1010 3
b10101010 @
b10101010 P
b10101010 A
b10101010 M
b10101010 C
b10101010 H
b1010 *
b1010 Y
b0 +
b0 D
b0 G
b0 J
b0 O
b0 X
b110100 5
#580
b11110110 2
#600
1#
#610
b100000 !
b100000 /
b100000 S
#620
b100100 .
b100100 Q
b100100 R
b100100 -
#630
0;
0=
b1 U
b0 W
b1010 6
b1010 >
b1010 F
b1010 I
b1010 L
b1010 N
b110 0
b100 1
b1 ,
b0 )
b0 4
b110000000010000000000000000 "
b110000000010000000000000000 %
#640
b110100 .
b110100 Q
b1010 7
b1010 E
b1010 T
1&
b1010 @
b1010 P
b1010 A
b1010 M
1:
0#
#650
b0 6
b0 >
b0 F
b0 I
b0 L
b0 N
b0 3
b101000 .
b101000 Q
b0 *
b0 Y
b1010 C
b1010 H
b101000 5
#660
1'
b0 7
b0 E
b0 T
b0 @
b0 P
b0 A
b0 M
b0 2
#670
b0 C
b0 H
#680
1#
#690
b101000 !
b101000 /
b101000 S
