src/reg_file.v
// Computer Architecture CO2070 - Lab 02
// Design: Register File of Simple Processor
// Author: Kisaru Liyanage
// Team : 06
// Members : E/22/014 , E/22/035

// Register File Module

module reg_file(
    IN,
    OUT1,
    OUT2,
    INADDRESS,
    OUT1ADDRESS,
    OUT2ADDRESS,
    WRITE,
    CLK,
    RESET
);


// Input Ports

// data input
input [7:0] IN;

// register addresses
input [2:0] INADDRESS;
input [2:0] OUT1ADDRESS;
input [2:0] OUT2ADDRESS;

// control signals
input WRITE;
input CLK;
input RESET;


// Output Ports

// output values from registers
output reg [7:0] OUT1;
output reg [7:0] OUT2;


// Register Array
// 8 registers
// each register contains 8 bits

reg [7:0] registers [7:0];


// Asynchronous Read
// outputs change immediately when:
// - read address changes
// - register values change

always @(
    OUT1ADDRESS or
    OUT2ADDRESS or
    registers[0] or
    registers[1] or
    registers[2] or
    registers[3] or
    registers[4] or
    registers[5] or
    registers[6] or
    registers[7]
)

begin

    // read delay
    #2;

    // read data from selected registers
    OUT1 = registers[OUT1ADDRESS];
    OUT2 = registers[OUT2ADDRESS];

end


// Synchronous Write and Reset
// operations happen only at positive clock edge

always @(posedge CLK)

begin

    // Reset all registers

    if(RESET)

    begin

        // reset delay
        #1;

        registers[0] = 8'b00000000;
        registers[1] = 8'b00000000;
        registers[2] = 8'b00000000;
        registers[3] = 8'b00000000;
        registers[4] = 8'b00000000;
        registers[5] = 8'b00000000;
        registers[6] = 8'b00000000;
        registers[7] = 8'b00000000;

    end


    // Write operation

    else if(WRITE)

    begin

        // write delay
        #1;

        // write input data into selected register
        registers[INADDRESS] = IN;

    end

end

endmodule

testbenches/reg_file_tb.v
// Computer Architecture CO2070 - Lab 02
// Design: Register File of Simple Processor
// Team : 06
// Members : E/22/014 , E/22/035

// Register File Module

`include "reg_file.v"

module reg_file_tb;
    
    reg [7:0] WRITEDATA;
    reg [2:0] WRITEREG, READREG1, READREG2;
    reg CLK, RESET, WRITEENABLE; 
    
    wire [7:0] REGOUT1, REGOUT2;
    
    
    // Instantiate Register File

    reg_file myregfile(
        WRITEDATA,
        REGOUT1,
        REGOUT2,
        WRITEREG,
        READREG1,
        READREG2,
        WRITEENABLE,
        CLK,
        RESET
    );
       
       
    // Apply Input Signals

    initial
    begin

        // initial clock value
        CLK = 1'b1;
        
        
        // generate waveform file for GTKWave
        $dumpfile("reg_file_wavedata.vcd");
        $dumpvars(0, reg_file_tb);
        
        
        // initial values

        RESET = 1'b0;
        WRITEENABLE = 1'b0;
        
        
        // Reset register file

        #4
        RESET = 1'b1;

        READREG1 = 3'd0;
        READREG2 = 3'd4;
        
        
        // Stop reset

        #6
        RESET = 1'b0;
        
        
        // Write value 95 into register 2

        #2

        WRITEREG = 3'd2;
        WRITEDATA = 8'd95;
        WRITEENABLE = 1'b1;
        
        
        // Disable writing

        #7
        WRITEENABLE = 1'b0;
        
        
        // Read register 2

        #1
        READREG1 = 3'd2;
        
        
        // Write value 28 into register 1

        #7

        WRITEREG = 3'd1;
        WRITEDATA = 8'd28;
        WRITEENABLE = 1'b1;

        READREG1 = 3'd1;
        
        
        // Disable writing

        #8
        WRITEENABLE = 1'b0;
        
        
        // Write value 6 into register 4

        #8

        WRITEREG = 3'd4;
        WRITEDATA = 8'd6;
        WRITEENABLE = 1'b1;
        
        
        // Change register 4 value to 15

        #8

        WRITEDATA = 8'd15;
        WRITEENABLE = 1'b1;
        
        
        // Disable writing

        #10
        WRITEENABLE = 1'b0;
        
        
        // Write value 50 into register 7

        #6

        WRITEREG = 3'd7;
        WRITEDATA = 8'd50;
        WRITEENABLE = 1'b1;
        
        
        // Disable writing

        #5
        WRITEENABLE = 1'b0;
        
        
        // Finish simulation

        #10
        $finish;

    end
    
    
    // Clock Generation
    // clock changes every 4 time units

    always
        #4 CLK = ~CLK;


    // Display values in terminal

    initial
    begin

        $monitor(
            "Time=%0d CLK=%b RESET=%b WRITE=%b WRITEREG=%0d WRITEDATA=%0d READREG1=%0d REGOUT1=%0d READREG2=%0d REGOUT2=%0d",
            $time,
            CLK,
            RESET,
            WRITEENABLE,
            WRITEREG,
            WRITEDATA,
            READREG1,
            REGOUT1,
            READREG2,
            REGOUT2
        );

    end


endmodule

testbenches/reg_file_wavedata.vcd
$date
	Sat Jun 06 22:04:47 2026
$end
$version
	Icarus Verilog
$end
$timescale
	1s
$end
$scope module reg_file_tb $end
$var wire 8 ! REGOUT2 [7:0] $end
$var wire 8 " REGOUT1 [7:0] $end
$var reg 1 # CLK $end
$var reg 3 $ READREG1 [2:0] $end
$var reg 3 % READREG2 [2:0] $end
$var reg 1 & RESET $end
$var reg 8 ' WRITEDATA [7:0] $end
$var reg 1 ( WRITEENABLE $end
$var reg 3 ) WRITEREG [2:0] $end
$scope module myregfile $end
$var wire 1 # CLK $end
$var wire 8 * IN [7:0] $end
$var wire 3 + INADDRESS [2:0] $end
$var wire 3 , OUT1ADDRESS [2:0] $end
$var wire 3 - OUT2ADDRESS [2:0] $end
$var wire 1 & RESET $end
$var wire 1 ( WRITE $end
$var reg 8 . OUT1 [7:0] $end
$var reg 8 / OUT2 [7:0] $end
$upscope $end
$upscope $end
$enddefinitions $end
$comment Show the parameter values. $end
$dumpall
$end
#0
$dumpvars
bx /
bx .
bx -
bx ,
bx +
bx *
bx )
0(
bx '
0&
bx %
bx $
1#
bx "
bx !
$end
#4
0#
b100 %
b100 -
b0 $
b0 ,
1&
#8
1#
#10
0&
#11
b0 !
b0 /
b0 "
b0 .
#12
1(
b1011111 '
b1011111 *
b10 )
b10 +
0#
#16
1#
#19
0(
#20
b10 $
b10 ,
0#
#22
b1011111 "
b1011111 .
#24
1#
#27
b1 $
b1 ,
1(
b11100 '
b11100 *
b1 )
b1 +
#28
0#
#29
b0 "
b0 .
#32
1#
#35
b11100 "
b11100 .
0(
#36
0#
#40
1#
#43
1(
b110 '
b110 *
b100 )
b100 +
#44
0#
#48
1#
#51
b110 !
b110 /
b1111 '
b1111 *
#52
0#
#56
1#
#59
b1111 !
b1111 /
#60
0#
#61
0(
#64
1#
#67
1(
b110010 '
b110010 *
b111 )
b111 +
#68
0#
#72
1#
0(
